pie_rise_instrumentals/__init__.py
pie_rise_instrumentals/utilits.py
pie_rise_instrumentals/working_api.py
piroschock_libraru_instruments-0.0.2.dist-info/METADATA
piroschock_libraru_instruments-0.0.2.dist-info/WHEEL
piroschock_libraru_instruments-0.0.2.dist-info/top_level.txt
piroschock_libraru_instruments-0.0.2.dist-info/RECORD
