Metadata-Version: 2.1
Name: piroschock_libraru_instruments
Version: 0.0.2
Summary: You`ve never seen anything like this, a library that contains many modern features...
Home-page: https://t.me/pie_rise_a_channel_8539
Author: Pie-Rise The Sound
Author-email: piroschock.riseng.853@internet.ru
Project-URL: VKontakte, https://vk.com/piroschock.frilance.work
Project-URL: Telegram Channel, https://t.me/pie_rise_a_channel_8539
Requires-Python: >=3.8.9
Requires-Dist: discord
Requires-Dist: vk-api
Requires-Dist: tqdm
Requires-Dist: segno
